{"ppb_form_data_order":["1435727004866,1435728118871,1435737895945,1435737945591,1435729571188"],"1435727004866_data":["{\"id\":\"1435727004866\",\"shortcode\":\"ppb_header\",\"ppb_header_title\":\"Vintage%20Radio\",\"ppb_header_slug\":\"\",\"ppb_header_subtitle\":\"Landscape%20\/%20Model%20\/%20Architecture\",\"ppb_header_width\":\"60%25\",\"ppb_header_textalign\":\"center\",\"ppb_header_padding\":\"50\",\"ppb_header_bgcolor\":\"\",\"ppb_header_fontcolor\":\"\",\"ppb_header_custom_css\":\"padding-bottom:%2020px%20!important;\",\"ppb_header_content\":\"\"}"],"1435727004866_size":["one"],"1435728118871_data":["{\"id\":\"1435728118871\",\"shortcode\":\"ppb_header\",\"ppb_header_title\":\"\",\"ppb_header_slug\":\"\",\"ppb_header_subtitle\":\"\",\"ppb_header_width\":\"70%25\",\"ppb_header_textalign\":\"left\",\"ppb_header_padding\":\"50\",\"ppb_header_bgcolor\":\"\",\"ppb_header_fontcolor\":\"\",\"ppb_header_custom_css\":\"padding-top:%200%20!important;\",\"ppb_header_content\":\"Sed%20ut%20perspiciatis%20unde%20omnis%20iste%20natus%20error%20sit%20voluptatem%20accusantium%20doloremque%20laudantium,%20totam%20rem%20aperiam,%20eaque%20ipsa%20quae%20ab%20illo%20inventore%20veritatis%20et%20quasi%20architecto%20beatae%20vitae%20dicta%20sunt%20explicabo.%20Nemo%20enim%20ipsam%20voluptatem%20quia%20voluptas%20sit%20aspernatur%20aut%20odit%20aut%20fugit.%20Vivamus%20at%20nibh%20tincidunt,%20bibendum%20ligula%20id.%20Nemo%20enim%20ipsam%20voluptatem%20quia%20\"}"],"1435728118871_size":["one"],"1435737895945_data":["{\"id\":\"1435737895945\",\"shortcode\":\"ppb_two_cols_images_no_space\",\"ppb_two_cols_images_no_space_title\":\"2%20Cols%20Images\",\"ppb_two_cols_images_no_space_slug\":\"\",\"ppb_two_cols_images_no_space_image1\":\"http:\/\/themes.themegoods2.com\/photome\/demo\/wp-content\/uploads\/2012\/08\/fTO1henYeTg.jpg\",\"ppb_two_cols_images_no_space_image2\":\"http:\/\/themes.themegoods2.com\/photome\/demo\/wp-content\/uploads\/2012\/08\/photo-1417436026361-a033044d901f.jpg\",\"ppb_two_cols_images_no_space_height\":\"720\",\"ppb_two_cols_images_no_space_display_caption\":\"0\",\"ppb_two_cols_images_no_space_padding\":\"0\",\"ppb_two_cols_images_no_space_custom_css\":\"\"}"],"1435737895945_size":["one"],"1435737945591_data":["{\"id\":\"1435737945591\",\"shortcode\":\"ppb_two_cols_images_no_space\",\"ppb_two_cols_images_no_space_title\":\"2%20Cols%20Images\",\"ppb_two_cols_images_no_space_slug\":\"\",\"ppb_two_cols_images_no_space_image1\":\"http:\/\/themes.themegoods2.com\/photome\/demo\/wp-content\/uploads\/2013\/06\/sea-nature-ocean-waves.jpeg\",\"ppb_two_cols_images_no_space_image2\":\"http:\/\/themes.themegoods2.com\/photome\/demo\/wp-content\/uploads\/2015\/06\/slider_2.jpg\",\"ppb_two_cols_images_no_space_height\":\"720\",\"ppb_two_cols_images_no_space_display_caption\":\"0\",\"ppb_two_cols_images_no_space_padding\":\"0\",\"ppb_two_cols_images_no_space_custom_css\":\"\"}"],"1435737945591_size":["one"],"1435729571188_data":["{\"id\":\"1435729571188\",\"shortcode\":\"ppb_text\",\"ppb_text_title\":\"Quote\",\"ppb_text_slug\":\"\",\"ppb_text_width\":\"70%25\",\"ppb_text_padding\":\"50\",\"ppb_text_bgcolor\":\"\",\"ppb_text_fontcolor\":\"\",\"ppb_text_custom_css\":\"\",\"ppb_text_content\":\"%3Cblockquote%3EDesign%20is%20not%20just%20what%20it%20looks%20like%20and%20feels%20like.%20Design%20is%20how%20it%20works.%3C\/blockquote%3E%0ASed%20ut%20perspiciatis%20unde%20omnis%20iste%20natus%20error%20sit%20voluptatem%20accusantium%20doloremque%20laudantium,%20totam%20rem%20aperiam,%20eaque%20ipsa%20quae%20ab%20illo%20inventore%20veritatis%20et%20quasi%20architecto%20beatae%20vitae%20dicta%20sunt%20explicabo.%20Nemo%20enim%20ipsam%20voluptatem%20quia%20voluptas%20sit%20aspernatur%20aut%20odit%20aut%20fugit.\"}"],"1435729571188_size":["one"]}